{
  "stem-1.png": [
    {
      "f": 0.05,
      "x": 0.6036,
      "angle": 158.17
    },
    {
      "f": 0.1,
      "x": 0.6607,
      "angle": 156.34
    },
    {
      "f": 0.15,
      "x": 0.7286,
      "angle": 155.75
    },
    {
      "f": 0.2,
      "x": 0.7893,
      "angle": 161.01
    },
    {
      "f": 0.25,
      "x": 0.8268,
      "angle": 168.68
    },
    {
      "f": 0.3,
      "x": 0.8464,
      "angle": 174.64
    },
    {
      "f": 0.35,
      "x": 0.8536,
      "angle": 175.71
    },
    {
      "f": 0.4,
      "x": 0.8679,
      "angle": 177.13
    },
    {
      "f": 0.45,
      "x": 0.8679,
      "angle": 181.79
    },
    {
      "f": 0.5,
      "x": 0.8589,
      "angle": 188.19
    },
    {
      "f": 0.55,
      "x": 0.8268,
      "angle": 192.01
    },
    {
      "f": 0.6,
      "x": 0.7982,
      "angle": 193.38
    },
    {
      "f": 0.65,
      "x": 0.7589,
      "angle": 198.35
    },
    {
      "f": 0.7,
      "x": 0.7036,
      "angle": 201.83
    },
    {
      "f": 0.75,
      "x": 0.6446,
      "angle": 208.01
    },
    {
      "f": 0.8,
      "x": 0.5518,
      "angle": 215.5
    },
    {
      "f": 0.85,
      "x": 0.4411,
      "angle": 221.62
    },
    {
      "f": 0.9,
      "x": 0.2982,
      "angle": 221.82
    },
    {
      "f": 0.95,
      "x": 0.1857,
      "angle": 218.26
    }
  ],
  "stem-2.png": [
    {
      "f": 0.05,
      "x": 0.1259,
      "angle": 177.08
    },
    {
      "f": 0.1,
      "x": 0.1335,
      "angle": 178.9
    },
    {
      "f": 0.15,
      "x": 0.1316,
      "angle": 180.37
    },
    {
      "f": 0.2,
      "x": 0.1316,
      "angle": 178.9
    },
    {
      "f": 0.25,
      "x": 0.1372,
      "angle": 176.71
    },
    {
      "f": 0.3,
      "x": 0.1485,
      "angle": 178.54
    },
    {
      "f": 0.35,
      "x": 0.1447,
      "angle": 180.37
    },
    {
      "f": 0.4,
      "x": 0.1466,
      "angle": 177.44
    },
    {
      "f": 0.45,
      "x": 0.1579,
      "angle": 174.53
    },
    {
      "f": 0.5,
      "x": 0.1748,
      "angle": 172.72
    },
    {
      "f": 0.55,
      "x": 0.1955,
      "angle": 171.29
    },
    {
      "f": 0.6,
      "x": 0.2199,
      "angle": 169.16
    },
    {
      "f": 0.65,
      "x": 0.2519,
      "angle": 167.05
    },
    {
      "f": 0.7,
      "x": 0.2876,
      "angle": 163.29
    },
    {
      "f": 0.75,
      "x": 0.3402,
      "angle": 159.04
    },
    {
      "f": 0.8,
      "x": 0.4004,
      "angle": 155.31
    },
    {
      "f": 0.85,
      "x": 0.4756,
      "angle": 143.95
    },
    {
      "f": 0.9,
      "x": 0.6147,
      "angle": 133.5
    },
    {
      "f": 0.95,
      "x": 0.7857,
      "angle": 130.71
    }
  ],
  "stem-3.png": [
    {
      "f": 0.05,
      "x": 0.9036,
      "angle": -177.8
    },
    {
      "f": 0.1,
      "x": 0.8994,
      "angle": -182.93
    },
    {
      "f": 0.15,
      "x": 0.9146,
      "angle": -172.71
    },
    {
      "f": 0.2,
      "x": 0.8719,
      "angle": -163.95
    },
    {
      "f": 0.25,
      "x": 0.8526,
      "angle": -169.14
    },
    {
      "f": 0.3,
      "x": 0.8306,
      "angle": -168.09
    },
    {
      "f": 0.35,
      "x": 0.8072,
      "angle": -168.79
    },
    {
      "f": 0.4,
      "x": 0.7879,
      "angle": -166.0
    },
    {
      "f": 0.45,
      "x": 0.7534,
      "angle": -161.61
    },
    {
      "f": 0.5,
      "x": 0.7163,
      "angle": -160.3
    },
    {
      "f": 0.55,
      "x": 0.6763,
      "angle": -158.69
    },
    {
      "f": 0.6,
      "x": 0.6322,
      "angle": -157.12
    },
    {
      "f": 0.65,
      "x": 0.5854,
      "angle": -156.19
    },
    {
      "f": 0.7,
      "x": 0.5372,
      "angle": -151.76
    },
    {
      "f": 0.75,
      "x": 0.4697,
      "angle": -147.67
    },
    {
      "f": 0.8,
      "x": 0.4008,
      "angle": -145.13
    },
    {
      "f": 0.85,
      "x": 0.3196,
      "angle": -143.67
    },
    {
      "f": 0.9,
      "x": 0.2424,
      "angle": -148.72
    },
    {
      "f": 0.95,
      "x": 0.1887,
      "angle": -153.49
    }
  ],
  "stem-4.png": [
    {
      "f": 0.05,
      "x": 0.2371,
      "angle": -179.37
    },
    {
      "f": 0.1,
      "x": 0.2347,
      "angle": -179.05
    },
    {
      "f": 0.15,
      "x": 0.23,
      "angle": -179.37
    },
    {
      "f": 0.2,
      "x": 0.23,
      "angle": -178.73
    },
    {
      "f": 0.25,
      "x": 0.2207,
      "angle": -176.51
    },
    {
      "f": 0.3,
      "x": 0.2042,
      "angle": -175.25
    },
    {
      "f": 0.35,
      "x": 0.1854,
      "angle": -176.51
    },
    {
      "f": 0.4,
      "x": 0.1784,
      "angle": -178.73
    },
    {
      "f": 0.45,
      "x": 0.1761,
      "angle": -178.73
    },
    {
      "f": 0.5,
      "x": 0.169,
      "angle": -178.41
    },
    {
      "f": 0.55,
      "x": 0.1643,
      "angle": -184.12
    },
    {
      "f": 0.6,
      "x": 0.1995,
      "angle": -186.01
    },
    {
      "f": 0.65,
      "x": 0.2089,
      "angle": -186.01
    },
    {
      "f": 0.7,
      "x": 0.2441,
      "angle": -190.05
    },
    {
      "f": 0.75,
      "x": 0.284,
      "angle": -191.58
    },
    {
      "f": 0.8,
      "x": 0.331,
      "angle": -194.29
    },
    {
      "f": 0.85,
      "x": 0.392,
      "angle": -196.94
    },
    {
      "f": 0.9,
      "x": 0.4601,
      "angle": -212.03
    },
    {
      "f": 0.95,
      "x": 0.6573,
      "angle": -222.93
    }
  ],
  "stem-5.png": [
    {
      "f": 0.05,
      "x": 0.0718,
      "angle": -176.11
    },
    {
      "f": 0.1,
      "x": 0.0668,
      "angle": -185.82
    },
    {
      "f": 0.15,
      "x": 0.0866,
      "angle": -209.27
    },
    {
      "f": 0.2,
      "x": 0.1485,
      "angle": -228.56
    },
    {
      "f": 0.25,
      "x": 0.2517,
      "angle": -243.87
    },
    {
      "f": 0.3,
      "x": 0.4455,
      "angle": -250.55
    },
    {
      "f": 0.35,
      "x": 0.6642,
      "angle": -247.9
    },
    {
      "f": 0.4,
      "x": 0.8045,
      "angle": -236.81
    },
    {
      "f": 0.45,
      "x": 0.887,
      "angle": -220.15
    },
    {
      "f": 0.5,
      "x": 0.9274,
      "angle": -200.49
    },
    {
      "f": 0.55,
      "x": 0.9414,
      "angle": -183.24
    },
    {
      "f": 0.6,
      "x": 0.9356,
      "angle": -164.49
    },
    {
      "f": 0.65,
      "x": 0.901,
      "angle": -143.85
    },
    {
      "f": 0.7,
      "x": 0.8292,
      "angle": -131.73
    },
    {
      "f": 0.75,
      "x": 0.7376,
      "angle": -126.01
    },
    {
      "f": 0.8,
      "x": 0.6287,
      "angle": -124.29
    },
    {
      "f": 0.85,
      "x": 0.5239,
      "angle": -128.75
    },
    {
      "f": 0.9,
      "x": 0.4472,
      "angle": -141.2
    },
    {
      "f": 0.95,
      "x": 0.4068,
      "angle": -150.97
    }
  ],
  "stem-6.png": [
    {
      "f": 0.05,
      "x": 0.8783,
      "angle": -113.0
    },
    {
      "f": 0.1,
      "x": 0.7217,
      "angle": -113.89
    },
    {
      "f": 0.15,
      "x": 0.5783,
      "angle": -117.65
    },
    {
      "f": 0.2,
      "x": 0.4681,
      "angle": -123.6
    },
    {
      "f": 0.25,
      "x": 0.3783,
      "angle": -129.31
    },
    {
      "f": 0.3,
      "x": 0.3058,
      "angle": -136.02
    },
    {
      "f": 0.35,
      "x": 0.25,
      "angle": -141.48
    },
    {
      "f": 0.4,
      "x": 0.2,
      "angle": -146.58
    },
    {
      "f": 0.45,
      "x": 0.1623,
      "angle": -152.37
    },
    {
      "f": 0.5,
      "x": 0.1304,
      "angle": -156.43
    },
    {
      "f": 0.55,
      "x": 0.1043,
      "angle": -160.76
    },
    {
      "f": 0.6,
      "x": 0.0841,
      "angle": -165.33
    },
    {
      "f": 0.65,
      "x": 0.0696,
      "angle": -169.2
    },
    {
      "f": 0.7,
      "x": 0.0587,
      "angle": -172.24
    },
    {
      "f": 0.75,
      "x": 0.0514,
      "angle": -177.19
    },
    {
      "f": 0.8,
      "x": 0.0522,
      "angle": -182.81
    },
    {
      "f": 0.85,
      "x": 0.058,
      "angle": -184.37
    },
    {
      "f": 0.9,
      "x": 0.0623,
      "angle": -189.29
    },
    {
      "f": 0.95,
      "x": 0.0797,
      "angle": -194.67
    }
  ],
  "stem-7.png": [
    {
      "f": 0.05,
      "x": 0.6202,
      "angle": 164.28
    },
    {
      "f": 0.1,
      "x": 0.6967,
      "angle": 164.02
    },
    {
      "f": 0.15,
      "x": 0.776,
      "angle": 170.02
    },
    {
      "f": 0.2,
      "x": 0.7923,
      "angle": 178.27
    },
    {
      "f": 0.25,
      "x": 0.7923,
      "angle": 181.15
    },
    {
      "f": 0.3,
      "x": 0.7814,
      "angle": 184.6
    },
    {
      "f": 0.35,
      "x": 0.7486,
      "angle": 183.16
    },
    {
      "f": 0.4,
      "x": 0.7514,
      "angle": 184.02
    },
    {
      "f": 0.45,
      "x": 0.7104,
      "angle": 187.44
    },
    {
      "f": 0.5,
      "x": 0.6803,
      "angle": 184.88
    },
    {
      "f": 0.55,
      "x": 0.6639,
      "angle": 187.16
    },
    {
      "f": 0.6,
      "x": 0.612,
      "angle": 191.09
    },
    {
      "f": 0.65,
      "x": 0.5574,
      "angle": 188.01
    },
    {
      "f": 0.7,
      "x": 0.5355,
      "angle": 188.29
    },
    {
      "f": 0.75,
      "x": 0.4781,
      "angle": 188.57
    },
    {
      "f": 0.8,
      "x": 0.4536,
      "angle": 189.42
    },
    {
      "f": 0.85,
      "x": 0.388,
      "angle": 195.72
    },
    {
      "f": 0.9,
      "x": 0.3005,
      "angle": 199.12
    },
    {
      "f": 0.95,
      "x": 0.1995,
      "angle": 200.4
    }
  ]
}